COPYING.txt
MANIFEST.in
setup.py
./__init__.py
./cmds.py
./config.py
./lpland.py
./pqm_submit.py
./tests/__init__.py
./tests/fakemethod.py
./tests/test_lpland.py
./tests/test_pqm_submit.py
bzr_pqm.egg-info/PKG-INFO
bzr_pqm.egg-info/SOURCES.txt
bzr_pqm.egg-info/dependency_links.txt
bzr_pqm.egg-info/requires.txt
bzr_pqm.egg-info/top_level.txt