Metadata-Version: 1.0
Name: bzr-pqm
Version: 1.4.0
Summary: bzr plugin to submit an email to a Patch Queue Manager
Home-page: https://launchpad.net/bzr-pqm
Author: John Arbash Meinel
Author-email: john@arbash-meinel.com
License: GNU GPL v2
Platform: UNKNOWN
